{"period": "M", "times": ["2024-01-31", "2024-02-29", "2024-03-31", "2024-04-30", "2024-05-31", "2024-06-30", "2024-07-31", "2024-08-31", "2024-09-30", "2024-10-31", "2024-11-30", "2024-12-31", "2025-01-31", "2025-02-28", "2025-03-31", "2025-04-30", "2025-05-31", "2025-06-30", "2025-07-31", "2025-08-31", "2025-09-30", "2025-10-31", "2025-11-30", "2025-12-31", "2026-01-31", "2026-02-28", "2026-03-31", "2026-04-30", "2026-05-31"], "rows": [{"time": "2024-01-31", "o": 5.63, "h": 7.03, "l": 5.54, "c": 5.92, "v": 9263909.040000001, "pct": 5.150976909413854}, {"time": "2024-02-29", "o": 5.56, "h": 5.56, "l": 4.08, "c": 5.36, "v": 5237074.44, "pct": -3.597122302158261}, {"time": "2024-03-31", "o": 5.74, "h": 5.74, "l": 4.97, "c": 5.27, "v": 4770170.370000001, "pct": -8.18815331010454}, {"time": "2024-04-30", "o": 5.26, "h": 6.11, "l": 5.22, "c": 5.5, "v": 6914409.74, "pct": 4.562737642585556}, {"time": "2024-05-31", "o": 5.46, "h": 5.84, "l": 5.23, "c": 5.3, "v": 3787397.7499999995, "pct": -2.9304029304029333}, {"time": "2024-06-30", "o": 5.31, "h": 5.32, "l": 4.77, "c": 4.95, "v": 1379714.85, "pct": -6.7796610169491425}, {"time": "2024-07-31", "o": 4.91, "h": 5.09, "l": 4.68, "c": 5.07, "v": 1384441.51, "pct": 3.258655804480654}, {"time": "2024-08-31", "o": 5.08, "h": 5.22, "l": 4.77, "c": 4.93, "v": 1407438.3, "pct": -2.9527559055118178}, {"time": "2024-09-30", "o": 4.92, "h": 5.79, "l": 4.64, "c": 5.79, "v": 1969023.79, "pct": 17.682926829268293}, {"time": "2024-10-31", "o": 6.37, "h": 6.44, "l": 5.46, "c": 6.04, "v": 5185558.04, "pct": -5.180533751962325}, {"time": "2024-11-30", "o": 5.99, "h": 6.78, "l": 5.71, "c": 6.12, "v": 5503927.989999999, "pct": 2.170283806343905}, {"time": "2024-12-31", "o": 6.13, "h": 6.51, "l": 5.67, "c": 5.83, "v": 3055311.0999999996, "pct": -4.893964110929851}, {"time": "2025-01-31", "o": 5.86, "h": 5.91, "l": 5.41, "c": 5.73, "v": 1995164.1099999999, "pct": -2.2184300341296908}, {"time": "2025-02-28", "o": 5.77, "h": 5.91, "l": 5.58, "c": 5.71, "v": 1916103.71, "pct": -1.0398613518197506}, {"time": "2025-03-31", "o": 5.72, "h": 6.32, "l": 5.61, "c": 6.01, "v": 2708900.5900000003, "pct": 5.069930069930071}, {"time": "2025-04-30", "o": 6.28, "h": 6.37, "l": 4.9, "c": 5.87, "v": 3063718.7399999998, "pct": -6.528662420382167}, {"time": "2025-05-31", "o": 5.88, "h": 6.33, "l": 5.88, "c": 6.04, "v": 1999794.6199999999, "pct": 2.721088435374152}, {"time": "2025-06-30", "o": 6.06, "h": 8.47, "l": 6.02, "c": 7.01, "v": 12652233.26, "pct": 15.67656765676568}, {"time": "2025-07-31", "o": 7.04, "h": 7.11, "l": 6.64, "c": 6.65, "v": 5836522.03, "pct": -5.539772727272723}, {"time": "2025-08-31", "o": 6.64, "h": 7.24, "l": 6.51, "c": 6.94, "v": 4870996.86, "pct": 4.518072289156637}, {"time": "2025-09-30", "o": 6.92, "h": 7.13, "l": 6.36, "c": 6.59, "v": 3896593.7899999996, "pct": -4.7687861271676315}, {"time": "2025-10-31", "o": 6.57, "h": 7.24, "l": 6.49, "c": 6.78, "v": 3512520.67, "pct": 3.1963470319634695}, {"time": "2025-11-30", "o": 6.78, "h": 7.32, "l": 6.5, "c": 6.71, "v": 3843188.78, "pct": -1.032448377581125}, {"time": "2025-12-31", "o": 6.78, "h": 6.9, "l": 6.19, "c": 6.48, "v": 2400570.54, "pct": -4.424778761061944}, {"time": "2026-01-31", "o": 6.74, "h": 9.54, "l": 6.48, "c": 8.46, "v": 9451327.620000001, "pct": 25.519287833827903}, {"time": "2026-02-28", "o": 7.63, "h": 8.98, "l": 7.61, "c": 8.96, "v": 6643095.75, "pct": 17.431192660550472}, {"time": "2026-03-31", "o": 9.86, "h": 11.94, "l": 8.12, "c": 8.24, "v": 13290649.559999999, "pct": -16.43002028397565}, {"time": "2026-04-30", "o": 8.24, "h": 8.62, "l": 7.78, "c": 8.19, "v": 6421286.16, "pct": -0.606796116504863}, {"time": "2026-05-31", "o": 8.03, "h": 8.11, "l": 7.75, "c": 7.82, "v": 1153532.0, "pct": -2.615193026151919}], "indicators": {"ma5": [null, null, null, null, 5.470000000000001, 5.276, 5.218, 5.15, 5.208, 5.356, 5.59, 5.742, 5.902, 5.886, 5.88, 5.83, 5.872, 6.128, 6.316, 6.502, 6.646000000000001, 6.794, 6.734, 6.7, 7.0040000000000004, 7.478, 7.7700000000000005, 8.065999999999999, 8.334], "ma10": [null, null, null, null, null, null, null, null, null, 5.413, 5.433, 5.4799999999999995, 5.526, 5.547, 5.618, 5.71, 5.807, 6.015, 6.101, 6.191000000000001, 6.238, 6.333, 6.431, 6.508, 6.753, 7.062, 7.282000000000001, 7.4, 7.517], "ma20": [null, null, null, null, null, null, null, null, null, null, null, null, null, null, null, null, null, null, null, 5.8020000000000005, 5.835500000000001, 5.906499999999999, 5.9785, 6.0275, 6.1855, 6.386, 6.544500000000001, 6.7075000000000005, 6.809], "ma30": [null, null, null, null, null, null, null, null, null, null, null, null, null, null, null, null, null, null, null, null, null, null, null, null, null, null, null, null, null], "ma60": [null, null, null, null, null, null, null, null, null, null, null, null, null, null, null, null, null, null, null, null, null, null, null, null, null, null, null, null, null, null, null, null, null, null, null, null, null, null, null, null, null, null, null, null, null, null, null, null, null, null, null, null, null, null, null, null, null, null, null], "ma120": [null, null, null, null, null, null, null, null, null, null, null, null, null, null, null, null, null, null, null, null, null, null, null, null, null, null, null, null, null, null, null, null, null, null, null, null, null, null, null, null, null, null, null, null, null, null, null, null, null, null, null, null, null, null, null, null, null, null, null, null, null, null, null, null, null, null, null, null, null, null, null, null, null, null, null, null, null, null, null, null, null, null, null, null, null, null, null, null, null, null, null, null, null, null, null, null, null, null, null, null, null, null, null, null, null, null, null, null, null, null, null, null, null, null, null, null, null, null, null], "ma240": [null, null, null, null, null, null, null, null, null, null, null, null, null, null, null, null, null, null, null, null, null, null, null, null, null, null, null, null, null, null, null, null, null, null, null, null, null, null, null, null, null, null, null, null, null, null, null, null, null, null, null, null, null, null, null, null, null, null, null, null, null, null, null, null, null, null, null, null, null, null, null, null, null, null, null, null, null, null, null, null, null, null, null, null, null, null, null, null, null, null, null, null, null, null, null, null, null, null, null, null, null, null, null, null, null, null, null, null, null, null, null, null, null, null, null, null, null, null, null, null, null, null, null, null, null, null, null, null, null, null, null, null, null, null, null, null, null, null, null, null, null, null, null, null, null, null, null, null, null, null, null, null, null, null, null, null, null, null, null, null, null, null, null, null, null, null, null, null, null, null, null, null, null, null, null, null, null, null, null, null, null, null, null, null, null, null, null, null, null, null, null, null, null, null, null, null, null, null, null, null, null, null, null, null, null, null, null, null, null, null, null, null, null, null, null, null, null, null, null, null, null, null, null, null, null, null, null, null, null, null, null, null, null, null, null, null, null, null, null], "dif": [0.0, -0.04467236467236457, -0.08634248098635577, -0.09965846976812731, -0.1249099314089106, -0.17119059302024908, -0.19592683111437204, -0.22424238140333586, -0.1752674720125995, -0.11495644645561143, -0.06001240709950206, -0.03941508387634585, -0.030805613158757517, -0.02530468181980705, 0.003225161044838387, 0.01437275689554518, 0.036504089748429, 0.13080636945084834, 0.1744813023293723, 0.22984506680879324, 0.24268169063957856, 0.2651299663971498, 0.2741121771314621, 0.2596781578819183, 0.4033588760438773, 0.5512185968141434, 0.6033455165422525, 0.6333213594455609, 0.6200736995043297], "dea": [0.0, -0.008934472934472915, -0.024416074544849488, -0.039464553589505055, -0.056553629153386166, -0.07948102192675875, -0.10277018376428142, -0.1270646232920923, -0.13670519303619375, -0.1323554437200773, -0.11788683639596226, -0.10219248589203898, -0.0879151113453827, -0.07539302544026756, -0.05966938814324637, -0.04486095913548806, -0.028587949358704647, 0.0032909144032059502, 0.037528991988439224, 0.07599220695251004, 0.10933010368992374, 0.14049007623136897, 0.1672144964113876, 0.18570722870549378, 0.22923755817317049, 0.2936337659013651, 0.3555761160295426, 0.4111251647127463, 0.452914871671063], "macd": [0.0, -0.07147578347578332, -0.12385281288301257, -0.12038783235724451, -0.13671260451104889, -0.18341914218698066, -0.18631329470018124, -0.1943555162224871, -0.07712455795281153, 0.03479799452893173, 0.11574885859292039, 0.12555480403138627, 0.11421899637325036, 0.10017668724092102, 0.12578909837616953, 0.11846743206206647, 0.1301840782142673, 0.2550309100952848, 0.27390462068186616, 0.30770571971256644, 0.26670317389930964, 0.24927978033156167, 0.21379536144014893, 0.147941858352849, 0.3482426357414137, 0.5151696618255567, 0.4955388010254199, 0.4443923894656292, 0.3343176556665334], "K": [50.0, 47.79661016949152, 45.31073446327683, 46.25235404896421, 44.62021343377275, 39.57731743042477, 37.571318964915946, 34.65206575062192, 42.42341106538636, 55.96588986279994, 60.36355274342426, 58.77819404078751, 56.163655840275794, 54.109103893517194, 57.4122997919398, 57.433745032632764, 60.096016937643014, 59.76522511062288, 56.18335268812767, 56.50318750637082, 53.44843686232377, 53.185979383472606, 52.357412959663336, 49.65750966685305, 56.602274204131554, 65.57575856033014, 55.60123034456792, 48.66168979492933, 41.890401892271726], "D": [50.0, 49.265536723163834, 47.947269303201494, 47.382297551789065, 46.461602845783624, 44.166841040664, 41.968333682081315, 39.52957770492819, 40.49418882508091, 45.651422504320585, 50.555465917355136, 53.29637529183259, 54.25213547464699, 54.204458280937054, 55.27373878460463, 55.99374086728067, 57.361166224068114, 58.162519186253036, 57.50279702021125, 57.1695938489311, 55.92920818672866, 55.014798585643305, 54.12900337698331, 52.63850547360656, 53.95976171711489, 57.8317606648533, 57.0882505580915, 54.279396970370776, 50.14973194433776], "J": [50.0, 44.85875706214691, 40.03766478342749, 43.99246704331449, 40.93743460975101, 30.398270209946304, 28.777289530585207, 24.8970418420094, 46.28185554599726, 76.59482457975865, 79.9797263955625, 69.74183153869734, 59.9866965715334, 53.91839511867748, 61.68942180661014, 60.31375336333694, 65.56571836479282, 62.970636959362565, 53.5444640239605, 55.17037482125028, 48.48689421351398, 49.5283409791312, 48.814232125023366, 43.695518053346035, 61.88729917816488, 81.06375435128383, 52.62718991752075, 37.42627544404645, 25.37174178813966]}}