{"rows": [{"time": "2024-01-31", "o": 1.791, "h": 1.791, "l": 1.728, "c": 1.791, "v": 140.0, "pct": 0.0}, {"time": "2024-02-29", "o": 1.619, "h": 1.948, "l": 1.619, "c": 1.766, "v": 1211.71, "pct": 9.079678814082769}, {"time": "2024-03-31", "o": 1.766, "h": 1.933, "l": 1.749, "c": 1.78, "v": 715.05, "pct": 0.7927519818799553}, {"time": "2024-04-30", "o": 1.778, "h": 1.832, "l": 1.778, "c": 1.832, "v": 1120.0, "pct": 3.0371203599550083}, {"time": "2024-05-31", "o": 1.787, "h": 1.818, "l": 1.78, "c": 1.806, "v": 1748.72, "pct": 1.063234471180757}, {"time": "2024-06-30", "o": 1.804, "h": 1.861, "l": 1.771, "c": 1.79, "v": 167.0, "pct": -0.7760532150776059}, {"time": "2024-07-31", "o": 1.776, "h": 1.803, "l": 1.77, "c": 1.779, "v": 128.59, "pct": 0.1689189189189128}, {"time": "2024-08-31", "o": 1.769, "h": 1.779, "l": 1.75, "c": 1.779, "v": 503.11, "pct": 0.5652911249293392}, {"time": "2024-09-30", "o": 1.763, "h": 1.839, "l": 1.758, "c": 1.839, "v": 684.02, "pct": 4.310833806012482}, {"time": "2024-10-31", "o": 1.866, "h": 1.928, "l": 1.799, "c": 1.875, "v": 904.26, "pct": 0.48231511254018744}, {"time": "2024-11-30", "o": 1.847, "h": 1.92, "l": 1.847, "c": 1.883, "v": 1701.01, "pct": 1.9491066594477549}, {"time": "2024-12-31", "o": 1.899, "h": 1.918, "l": 1.882, "c": 1.912, "v": 729.06, "pct": 0.6845708267509163}, {"time": "2025-01-31", "o": 1.869, "h": 1.926, "l": 1.869, "c": 1.902, "v": 1086.54, "pct": 1.7656500802568174}, {"time": "2025-02-28", "o": 1.902, "h": 1.997, "l": 1.867, "c": 1.944, "v": 297.15999999999997, "pct": 2.2082018927444818}, {"time": "2025-03-31", "o": 1.848, "h": 1.938, "l": 1.81, "c": 1.846, "v": 952.15, "pct": -0.10822510822510831}, {"time": "2025-04-30", "o": 1.769, "h": 1.84, "l": 1.646, "c": 1.743, "v": 1541.8899999999999, "pct": -1.4697569248162692}, {"time": "2025-05-31", "o": 1.763, "h": 1.813, "l": 1.732, "c": 1.749, "v": 802.0699999999999, "pct": -0.7941009642654447}, {"time": "2025-06-30", "o": 1.763, "h": 1.867, "l": 1.763, "c": 1.858, "v": 1588.17, "pct": 5.38854225751561}, {"time": "2025-07-31", "o": 1.87, "h": 2.091, "l": 1.869, "c": 2.059, "v": 1062.19, "pct": 10.106951871657756}, {"time": "2025-08-31", "o": 2.047, "h": 2.607, "l": 2.046, "c": 2.565, "v": 2926.5499999999997, "pct": 25.30532486565705}, {"time": "2025-09-30", "o": 2.58, "h": 2.931, "l": 2.35, "c": 2.835, "v": 12081.669999999998, "pct": 9.883720930232553}, {"time": "2025-10-31", "o": 2.861, "h": 3.01, "l": 2.6, "c": 2.847, "v": 26598.67, "pct": -0.48933939182104974}, {"time": "2025-11-30", "o": 2.821, "h": 2.898, "l": 2.488, "c": 2.638, "v": 8365.119999999999, "pct": -6.487061325771013}, {"time": "2025-12-31", "o": 2.638, "h": 3.133, "l": 2.614, "c": 2.953, "v": 4946.51, "pct": 11.940864291129643}, {"time": "2026-01-31", "o": 2.983, "h": 3.298, "l": 2.906, "c": 3.223, "v": 23161.01, "pct": 8.045591686221917}, {"time": "2026-02-28", "o": 3.217, "h": 3.326, "l": 2.888, "c": 3.221, "v": 11983.52, "pct": 0.12433944668946233}, {"time": "2026-03-31", "o": 3.19, "h": 3.364, "l": 2.994, "c": 3.211, "v": 38888.3, "pct": 0.6583072100313451}, {"time": "2026-04-30", "o": 3.212, "h": 4.329, "l": 3.148, "c": 4.02, "v": 76278.74999999999, "pct": 25.155666251556642}, {"time": "2026-05-31", "o": 4.06, "h": 4.408, "l": 4.053, "c": 4.375, "v": 7214.870000000001, "pct": 7.758620689655182}], "indicators": {"ma5": [null, null, null, null, 1.795, 1.7948, 1.7974, 1.7972000000000001, 1.7986, 1.8123999999999998, 1.831, 1.8576000000000001, 1.8821999999999999, 1.9032, 1.8974, 1.8694, 1.8368000000000002, 1.828, 1.8510000000000002, 1.9948000000000001, 2.2132, 2.4328, 2.5888, 2.7676, 2.8991999999999996, 2.9764, 3.0492, 3.3256, 3.6100000000000003], "ma10": [null, null, null, null, null, null, null, null, null, 1.8036999999999999, 1.8129000000000002, 1.8275, 1.8397, 1.8509, 1.8549, 1.8501999999999998, 1.8472000000000002, 1.8551000000000002, 1.8771, 1.9461, 2.0413, 2.1348, 2.2084, 2.3093, 2.447, 2.5948, 2.741, 2.9572, 3.1887999999999996], "ma20": [null, null, null, null, null, null, null, null, null, null, null, null, null, null, null, null, null, null, null, 1.8748999999999998, 1.9271, 1.98115, 2.02405, 2.0801, 2.15095, 2.2225, 2.2941, 2.40615, 2.53295], "ma30": [null, null, null, null, null, null, null, null, null, null, null, null, null, null, null, null, null, null, null, null, null, null, null, null, null, null, null, null, null], "ma60": [null, null, null, null, null, null, null, null, null, null, null, null, null, null, null, null, null, null, null, null, null, null, null, null, null, null, null, null, null, null, null, null, null, null, null, null, null, null, null, null, null, null, null, null, null, null, null, null, null, null, null, null, null, null, null, null, null, null, null], "ma120": [null, null, null, null, null, null, null, null, null, null, null, null, null, null, null, null, null, null, null, null, null, null, null, null, null, null, null, null, null, null, null, null, null, null, null, null, null, null, null, null, null, null, null, null, null, null, null, null, null, null, null, null, null, null, null, null, null, null, null, null, null, null, null, null, null, null, null, null, null, null, null, null, null, null, null, null, null, null, null, null, null, null, null, null, null, null, null, null, null, null, null, null, null, null, null, null, null, null, null, null, null, null, null, null, null, null, null, null, null, null, null, null, null, null, null, null, null, null, null], "ma240": [null, null, null, null, null, null, null, null, null, null, null, null, null, null, null, null, null, null, null, null, null, null, null, null, null, null, null, null, null, null, null, null, null, null, null, null, null, null, null, null, null, null, null, null, null, null, null, null, null, null, null, null, null, null, null, null, null, null, null, null, null, null, null, null, null, null, null, null, null, null, null, null, null, null, null, null, null, null, null, null, null, null, null, null, null, null, null, null, null, null, null, null, null, null, null, null, null, null, null, null, null, null, null, null, null, null, null, null, null, null, null, null, null, null, null, null, null, null, null, null, null, null, null, null, null, null, null, null, null, null, null, null, null, null, null, null, null, null, null, null, null, null, null, null, null, null, null, null, null, null, null, null, null, null, null, null, null, null, null, null, null, null, null, null, null, null, null, null, null, null, null, null, null, null, null, null, null, null, null, null, null, null, null, null, null, null, null, null, null, null, null, null, null, null, null, null, null, null, null, null, null, null, null, null, null, null, null, null, null, null, null, null, null, null, null, null, null, null, null, null, null, null, null, null, null, null, null, null, null, null, null, null, null, null, null, null, null, null, null], "dif": [0.0, -0.001994301994301839, -0.002417253106711703, 0.0014270701312204537, 0.0023486673104409217, 0.001767597666691323, 0.00041470723165448753, -0.0006499756702307291, 0.0033096029755312895, 0.009245915555823325, 0.014429682784760534, 0.020639988359742567, 0.02447267804544384, 0.030547034032298637, 0.027140366682600225, 0.015945509167222705, 0.007471526678910045, 0.009442377701697868, 0.026913074341184506, 0.08065891274145254, 0.14338674724033562, 0.1918557144717643, 0.2109712219667954, 0.24867173385644303, 0.29691376757219023, 0.33116705589567097, 0.3534319734608409, 0.4313838949325741, 0.5158603702174638], "dea": [0.0, -0.00039886039886036787, -0.000802538940430635, -0.0003566171261004173, 0.0001844397612078505, 0.000501071342304545, 0.00048379852017453357, 0.0002570436820934811, 0.0008675555407810429, 0.0025432275437894994, 0.0049205185919837064, 0.008064412545535478, 0.01134606564551715, 0.015186259322873447, 0.017577080794818803, 0.017250766469299586, 0.015294918511221679, 0.014124410349316918, 0.016682143147690436, 0.029477497066442856, 0.05225934710122142, 0.08017862057533001, 0.1063371408536231, 0.13480405945418708, 0.16722600107778773, 0.20001421204136438, 0.23069776432525968, 0.2708349904467226, 0.31984006640087087], "macd": [0.0, -0.0031908831908829425, -0.003229428332562136, 0.003567374514641742, 0.0043284550984661425, 0.0025330526487735558, -0.00013818257704009207, -0.0018140387046484204, 0.004884094869500493, 0.01340537602406765, 0.019018328385553653, 0.02515115162841418, 0.02625322479985338, 0.03072154941885038, 0.019126571775562845, -0.002610514604153763, -0.015646783664623267, -0.0093640652952381, 0.02046186238698814, 0.10236283135001936, 0.1822548002782284, 0.22335418779286859, 0.20926816222634462, 0.2277353488045119, 0.259375532988805, 0.2623056877086132, 0.2454684182711624, 0.32109780897170304, 0.3920406076331858], "K": [50.0, 48.226950354609926, 48.46335697399527, 53.88945176179219, 54.87260309955346, 53.906963363228144, 52.14871519048035, 50.97654974198183, 56.274133465272584, 63.45327236084029, 66.57754389273408, 74.72210791350811, 78.27915808466082, 78.36694209692635, 65.2000936516621, 52.678504979550624, 44.90057976794354, 50.0666733115825, 64.31411179573664, 74.75259204696698, 80.67812232443713, 83.13536600710276, 79.66600158049275, 82.40903131593485, 86.67626353373944, 88.87822559319034, 89.17411249133536, 88.27113412694368, 91.64625657053776], "D": [50.0, 49.408983451536635, 49.093774625689505, 50.692333671057064, 52.08575681388919, 52.692825663668835, 52.51145550593934, 51.999820251286835, 53.42459132261541, 56.7674850020237, 60.03750463226049, 64.93237239267637, 69.38130095667118, 72.37651467008956, 69.98437433061373, 64.21575121359268, 57.777360731709635, 55.207131591667256, 58.24279165969038, 63.746058455449244, 69.39007974511188, 73.97184183244217, 75.86989508179235, 78.04960715983985, 80.92515928447304, 83.5761813873788, 85.44215842203099, 86.38515032366854, 88.13885240595827], "J": [50.0, 45.86288416075651, 47.202521670606785, 60.28368794326242, 60.446295670881995, 56.33523876234675, 51.42323455956239, 48.9300087233718, 61.97321775058691, 76.82484707847347, 79.65762241368128, 94.30157895517158, 96.0748723406401, 90.34779695059993, 55.63153229375885, 29.60401251146652, 19.147017840411337, 39.78575675141299, 76.45675206782914, 96.76565923000246, 103.25420748308761, 101.46241435642395, 87.25821457789354, 91.12787962812487, 98.17847203227228, 99.48231400481342, 96.63802062994415, 92.04310173349393, 98.66106489969675]}}