{"rows": [{"time": "2024-01-31", "o": 1.491, "h": 1.491, "l": 1.203, "c": 1.203, "v": 15102.480000000001, "pct": -19.315895372233403}, {"time": "2024-02-29", "o": 1.2, "h": 1.444, "l": 1.091, "c": 1.389, "v": 26284.86, "pct": 15.750000000000005}, {"time": "2024-03-31", "o": 1.413, "h": 1.589, "l": 1.401, "c": 1.472, "v": 39586.88, "pct": 4.175513092710541}, {"time": "2024-04-30", "o": 1.478, "h": 1.525, "l": 1.36, "c": 1.516, "v": 60690.57, "pct": 2.5710419485791633}, {"time": "2024-05-31", "o": 1.52, "h": 1.534, "l": 1.452, "c": 1.48, "v": 28062.320000000003, "pct": -2.6315789473684235}, {"time": "2024-06-30", "o": 1.45, "h": 1.597, "l": 1.45, "c": 1.504, "v": 29915.87, "pct": 3.7241379310344858}, {"time": "2024-07-31", "o": 1.504, "h": 1.541, "l": 1.345, "c": 1.393, "v": 21762.29, "pct": -7.380319148936169}, {"time": "2024-08-31", "o": 1.409, "h": 1.41, "l": 1.236, "c": 1.316, "v": 7560.18, "pct": -6.600425833924767}, {"time": "2024-09-30", "o": 1.281, "h": 1.529, "l": 1.233, "c": 1.529, "v": 15608.35, "pct": 19.35987509758002}, {"time": "2024-10-31", "o": 1.682, "h": 1.741, "l": 1.502, "c": 1.625, "v": 60210.46, "pct": -3.3888228299643246}, {"time": "2024-11-30", "o": 1.614, "h": 1.77, "l": 1.51, "c": 1.624, "v": 39513.619999999995, "pct": 0.6195786864931851}, {"time": "2024-12-31", "o": 1.596, "h": 1.718, "l": 1.534, "c": 1.56, "v": 44202.380000000005, "pct": -2.2556390977443628}, {"time": "2025-01-31", "o": 1.556, "h": 1.656, "l": 1.494, "c": 1.584, "v": 17237.62, "pct": 1.7994858611825209}, {"time": "2025-02-28", "o": 1.589, "h": 1.629, "l": 1.451, "c": 1.511, "v": 26875.640000000003, "pct": -4.908747640025178}, {"time": "2025-03-31", "o": 1.511, "h": 1.587, "l": 1.468, "c": 1.469, "v": 13104.639999999998, "pct": -2.7796161482461823}, {"time": "2025-04-30", "o": 1.469, "h": 1.494, "l": 1.215, "c": 1.38, "v": 21608.149999999998, "pct": -6.058543226684832}, {"time": "2025-05-31", "o": 1.4, "h": 1.495, "l": 1.366, "c": 1.465, "v": 10017.5, "pct": 4.642857142857156}, {"time": "2025-06-30", "o": 1.474, "h": 1.633, "l": 1.459, "c": 1.611, "v": 43586.55, "pct": 9.294436906377205}, {"time": "2025-07-31", "o": 1.6, "h": 2.025, "l": 1.591, "c": 1.975, "v": 89346.06000000001, "pct": 23.4375}, {"time": "2025-08-31", "o": 1.978, "h": 2.308, "l": 1.974, "c": 2.288, "v": 80808.88, "pct": 15.672396359959547}, {"time": "2025-09-30", "o": 2.289, "h": 2.368, "l": 2.085, "c": 2.132, "v": 50344.659999999996, "pct": -6.858890345128878}, {"time": "2025-10-31", "o": 2.137, "h": 2.198, "l": 1.965, "c": 2.176, "v": 12277.9, "pct": 1.8249883013570494}, {"time": "2025-11-30", "o": 2.156, "h": 2.288, "l": 1.96, "c": 2.101, "v": 18723.67, "pct": -2.551020408163273}, {"time": "2025-12-31", "o": 2.116, "h": 2.499, "l": 2.088, "c": 2.348, "v": 51659.28, "pct": 10.96408317580339}, {"time": "2026-01-31", "o": 2.33, "h": 2.419, "l": 2.189, "c": 2.368, "v": 27888.079999999994, "pct": 1.6309012875536397}, {"time": "2026-02-28", "o": 2.365, "h": 2.38, "l": 2.23, "c": 2.362, "v": 6257.5599999999995, "pct": -0.12684989429175955}, {"time": "2026-03-31", "o": 2.332, "h": 2.386, "l": 2.151, "c": 2.308, "v": 20933.11, "pct": -1.0291595197255583}, {"time": "2026-04-30", "o": 2.335, "h": 2.899, "l": 2.313, "c": 2.848, "v": 40294.58, "pct": 21.97002141327623}, {"time": "2026-05-31", "o": 2.876, "h": 3.07, "l": 2.876, "c": 3.068, "v": 6301.09, "pct": 6.6759388038943035}], "indicators": {"ma5": [null, null, null, null, 1.4120000000000001, 1.4722, 1.473, 1.4418, 1.4444, 1.4734, 1.4974, 1.5308, 1.5844, 1.5808, 1.5496, 1.5008, 1.4818, 1.4872, 1.58, 1.7437999999999998, 1.8942, 2.0364, 2.1344000000000003, 2.209, 2.225, 2.271, 2.2974, 2.4468, 2.5908], "ma10": [null, null, null, null, null, null, null, null, null, 1.4426999999999999, 1.4848000000000001, 1.5019, 1.5131000000000001, 1.5126, 1.5115, 1.4990999999999999, 1.5063, 1.5358, 1.5804, 1.6466999999999998, 1.6975000000000002, 1.7591, 1.8108, 1.8945, 1.9844000000000002, 2.0826000000000002, 2.1669, 2.2906, 2.3998999999999997], "ma20": [null, null, null, null, null, null, null, null, null, null, null, null, null, null, null, null, null, null, null, 1.5447, 1.59115, 1.6305, 1.6619499999999998, 1.70355, 1.7479500000000001, 1.79085, 1.8366, 1.9132000000000002, 1.9901499999999999], "ma30": [null, null, null, null, null, null, null, null, null, null, null, null, null, null, null, null, null, null, null, null, null, null, null, null, null, null, null, null, null], "ma60": [null, null, null, null, null, null, null, null, null, null, null, null, null, null, null, null, null, null, null, null, null, null, null, null, null, null, null, null, null, null, null, null, null, null, null, null, null, null, null, null, null, null, null, null, null, null, null, null, null, null, null, null, null, null, null, null, null, null, null], "ma120": [null, null, null, null, null, null, null, null, null, null, null, null, null, null, null, null, null, null, null, null, null, null, null, null, null, null, null, null, null, null, null, null, null, null, null, null, null, null, null, null, null, null, null, null, null, null, null, null, null, null, null, null, null, null, null, null, null, null, null, null, null, null, null, null, null, null, null, null, null, null, null, null, null, null, null, null, null, null, null, null, null, null, null, null, null, null, null, null, null, null, null, null, null, null, null, null, null, null, null, null, null, null, null, null, null, null, null, null, null, null, null, null, null, null, null, null, null, null, null], "ma240": [null, null, null, null, null, null, null, null, null, null, null, null, null, null, null, null, null, null, null, null, null, null, null, null, null, null, null, null, null, null, null, null, null, null, null, null, null, null, null, null, null, null, null, null, null, null, null, null, null, null, null, null, null, null, null, null, null, null, null, null, null, null, null, null, null, null, null, null, null, null, null, null, null, null, null, null, null, null, null, null, null, null, null, null, null, null, null, null, null, null, null, null, null, null, null, null, null, null, null, null, null, null, null, null, null, null, null, null, null, null, null, null, null, null, null, null, null, null, null, null, null, null, null, null, null, null, null, null, null, null, null, null, null, null, null, null, null, null, null, null, null, null, null, null, null, null, null, null, null, null, null, null, null, null, null, null, null, null, null, null, null, null, null, null, null, null, null, null, null, null, null, null, null, null, null, null, null, null, null, null, null, null, null, null, null, null, null, null, null, null, null, null, null, null, null, null, null, null, null, null, null, null, null, null, null, null, null, null, null, null, null, null, null, null, null, null, null, null, null, null, null, null, null, null, null, null, null, null, null, null, null, null, null, null, null, null, null, null, null], "dif": [0.0, 0.01483760683760682, 0.03291450556407827, 0.050212195386081904, 0.06032050284906387, 0.0694672337348865, 0.06698712563990572, 0.05813818481745736, 0.06753416354838881, 0.08178418490682904, 0.09193694597219593, 0.09373826081289982, 0.0959958349950707, 0.09084725824326645, 0.0824277492981973, 0.06779220526091301, 0.062333676966620066, 0.06899342058828095, 0.10246195566977256, 0.15248474576872173, 0.17749422808819793, 0.19857579710672568, 0.20684681788070902, 0.2306734373716568, 0.24830770121930312, 0.25881537003191135, 0.25979071887333505, 0.30067122615509634, 0.346823518456703], "dea": [0.0, 0.0029675213675213643, 0.008956918206832747, 0.01720797364268258, 0.025830479483958838, 0.03455783033414438, 0.04104368939529665, 0.044462588479728796, 0.049076903493460805, 0.055618359776134454, 0.06288207701534676, 0.06905331377485738, 0.07444181801890004, 0.07772290606377333, 0.07866387471065812, 0.0764895408207091, 0.0736583680498913, 0.07272537855756923, 0.0786726939800099, 0.09343510433775226, 0.1102469290878414, 0.12791270269161825, 0.1436995257294364, 0.1610943080578805, 0.17853698669016504, 0.19459266335851433, 0.20763227446147847, 0.22624006480020206, 0.2503567555315023], "macd": [0.0, 0.02374017094017091, 0.04791517471449104, 0.06600844348679866, 0.06898004673021008, 0.06981880680148425, 0.05188687248921814, 0.02735119267545713, 0.03691452010985602, 0.05233165026138917, 0.058109737913698334, 0.049369894076084886, 0.04310803395234131, 0.02624870435898624, 0.007527749175078341, -0.017394671119592198, -0.02264938216654247, -0.007463915938576565, 0.04757852337952534, 0.11809928286193894, 0.13449459800071306, 0.14132618883021486, 0.12629458430254525, 0.1391582586275526, 0.13954142905827616, 0.12844541334679405, 0.10431688882371315, 0.14886232270978855, 0.19293352585040147], "K": [50.0, 58.16666666666666, 64.27978580990629, 71.30031236055332, 73.57102484010113, 76.25420101329534, 70.73073216433129, 61.9759558302393, 70.17105882753765, 74.16532126964049, 73.71418686753191, 69.44074282788905, 68.08153804913275, 62.644054540514304, 56.41198918467558, 47.51790269969362, 46.69361681481077, 54.91286166032429, 67.88429460482524, 77.97958768104543, 78.49694397007539, 80.11389210609825, 79.02360080851764, 82.09569233548112, 84.2097201624596, 85.08212113394742, 83.04299999238197, 86.88489669353685, 91.19653773563117], "D": [50.0, 52.722222222222214, 56.574743418116896, 61.48326639892903, 65.51251921265306, 69.09307981286715, 69.63896393002184, 67.08462789676099, 68.11343820701987, 70.13073256122674, 71.32521732999513, 70.69705916262643, 69.82521879146186, 67.43149737447933, 63.75832797787808, 58.344852885149926, 54.4611075283702, 54.61169223902156, 59.03589302762278, 65.350457912097, 69.73261993142313, 73.19304398964816, 75.13656292927132, 77.45627273134124, 79.70742187504736, 81.49898829468071, 82.01365886058113, 83.63740480489969, 86.15711578181018], "J": [50.0, 69.05555555555554, 79.68987059348507, 90.93440428380188, 89.68803609499727, 90.57644341415173, 72.91426863295015, 51.75861169719593, 74.28630006857321, 82.23449868646799, 78.49212594260547, 66.92811015841431, 64.59417656447451, 53.06916887258424, 41.71931159827059, 25.864002328781012, 31.158635387691916, 55.515200502929744, 85.58109775923018, 103.2378472189423, 96.02559204737992, 93.95558833899841, 86.79767656701028, 91.37453154376087, 93.2143167372841, 92.24838681248085, 85.10168225598363, 93.37988047081114, 101.27538164327314]}}